dashinfer.libs/libgomp-a34b3233.so.1.0.0
dashinfer/__init__.py
dashinfer/allspark/__init__.py
dashinfer/allspark/client.py
dashinfer/allspark/engine_utils.py
dashinfer/allspark/generation_config.py
dashinfer/allspark/quantization.py
dashinfer/allspark/cpu_gemm_config.py
dashinfer/allspark/runtime_config.py
dashinfer/allspark/_allspark.cpython-310-x86_64-linux-gnu.so
dashinfer/allspark/model_config.py
dashinfer/allspark/engine.py
dashinfer/allspark/prompt_utils.py
dashinfer/allspark/arbiter_fileclient.py
dashinfer/allspark/model_loader.py
dashinfer/allspark/quant/__init__.py
dashinfer/allspark/quant/gptq_iq_adapter.py
dashinfer/allspark/quant/quantization_config.py
dashinfer/allspark/quant/quantization_config_gptq.py
dashinfer/allspark/quant/quantization_config_iq.py
dashinfer/allspark/config/diconfig.py
dashinfer/allspark/model/chatglm_v1.py
dashinfer/allspark/model/utils.py
dashinfer/allspark/model/chatglm_v4.py
dashinfer/allspark/model/__init__.py
dashinfer/allspark/model/qwen_v15.py
dashinfer/allspark/model/llama_v2.py
dashinfer/allspark/model/qwen_v10.py
dashinfer/allspark/model/llama_v3.py
dashinfer/allspark/model/qwen_v20.py
dashinfer/allspark/model/qwencode_v20.py
dashinfer/allspark/model/baichuan_v2.py
dashinfer/allspark/model/qwen_v20_moe.py
dashinfer/allspark/model/quantization_utils.py
dashinfer/allspark/model/model_base.py
dashinfer/allspark/model/baichuan_v1.py
dashinfer/allspark/model/llama.py
dashinfer/allspark/model/chatglm_v2.py
dashinfer/allspark/model/qwen_v1_config.py
dashinfer/allspark/model/chatglm_v3.py
dashinfer-2.1.0.dist-info/top_level.txt
dashinfer-2.1.0.dist-info/METADATA
dashinfer-2.1.0.dist-info/RECORD
dashinfer-2.1.0.dist-info/WHEEL
