Metadata-Version: 2.2
Name: dashinfer
Version: 2.1.0
Summary: DashInfer is a native inference engine for Pre-trained Large Language Models (LLMs) developed by Tongyi Laboratory.
Author: DashInfer team
Author-email: Dash-Infer@alibabacloud.com
License: Apache License 2.0
Classifier: Development Status :: 4 - Beta
Classifier: License :: OSI Approved :: Apache Software License
Classifier: Operating System :: OS Independent
Classifier: Programming Language :: Python :: 3
Classifier: Programming Language :: Python :: 3.8
Classifier: Programming Language :: Python :: 3.10
Requires-Python: >=3.8
Requires-Dist: transformers>=4.40.0
Requires-Dist: torch
Requires-Dist: ruamel.yaml
Dynamic: author
Dynamic: author-email
Dynamic: classifier
Dynamic: license
Dynamic: requires-dist
Dynamic: requires-python
Dynamic: summary
